{"pb_id": "soft-owl-topaz", "boltz2": {"status": "ok", "dG": null, "kd": 1.7e-08, "pkd": 7.769551078621726, "source_path": "structures/boltz2/soft-owl-topaz.cif"}, "chai": {"status": "ok", "dG": null, "kd": 1.1e-06, "pkd": 5.958607314841775, "source_path": "structures/chai/soft-owl-topaz.cif"}, "protenix": {"status": "ok", "dG": null, "kd": 2e-07, "pkd": 6.698970004336019, "source_path": "structures/protenix/soft-owl-topaz.cif"}, "af2m": {"status": "ok", "dG": null, "kd": 1.8e-10, "pkd": 9.744727494896694, "source_path": "structures/af2m/soft-owl-topaz.pdb"}}