{"pb_id": "strong-gecko-flint", "boltz2": {"status": "ok", "dG": null, "kd": 4.7e-09, "pkd": 8.327902142064282, "source_path": "structures/boltz2/strong-gecko-flint.cif"}, "chai": {"status": "ok", "dG": null, "kd": 7.2e-11, "pkd": 10.142667503568731, "source_path": "structures/chai/strong-gecko-flint.cif"}, "protenix": {"status": "ok", "dG": null, "kd": 2.3e-07, "pkd": 6.638272163982407, "source_path": "structures/protenix/strong-gecko-flint.cif"}, "af2m": {"status": "ok", "dG": null, "kd": 1.4e-09, "pkd": 8.853871964321762, "source_path": "structures/af2m/strong-gecko-flint.pdb"}}