{"pb_id": "wild-kiwi-opal", "boltz2": {"status": "ok", "dG": null, "kd": 1.7e-08, "pkd": 7.769551078621726, "source_path": "structures/boltz2/wild-kiwi-opal.cif"}, "chai": {"status": "ok", "dG": null, "kd": 3.7e-10, "pkd": 9.431798275933005, "source_path": "structures/chai/wild-kiwi-opal.cif"}, "protenix": {"status": "ok", "dG": null, "kd": 1e-06, "pkd": 6.0, "source_path": "structures/protenix/wild-kiwi-opal.cif"}, "af2m": {"status": "ok", "dG": null, "kd": 6.8e-14, "pkd": 13.167491087293763, "source_path": "structures/af2m/wild-kiwi-opal.pdb"}}