{"pb_id": "lunar-falcon-lotus", "results": {"esmfold": {"pb_id": "lunar-falcon-lotus", "predictor": "esmfold", "status": "error: '_atom_site.occupancy'", "rosetta_total_per_aa": null, "rosetta_fa_atr_per_aa": null, "rosetta_fa_rep_per_aa": null, "rosetta_fa_sol_per_aa": null, "rosetta_fa_elec_per_aa": null, "rosetta_hbond_sr_bb_per_aa": null, "rosetta_hbond_lr_bb_per_aa": null, "rosetta_hbond_bb_sc_per_aa": null, "rosetta_hbond_sc_per_aa": null, "rosetta_rama_prepro_per_aa": null, "rosetta_fa_dun_per_aa": null, "evoef2_total_per_aa": null, "budeff_total_per_aa": null, "budeff_steric_per_aa": null, "budeff_desolvation_per_aa": null, "budeff_charge_per_aa": null, "budeff_interaction_total": null, "budeff_interaction_steric": null, "budeff_interaction_desolvation": null, "budeff_interaction_charge": null, "isoelectric_point": null, "molecular_weight": null, "num_residues": null, "instability_index": null, "gravy": null}, "boltz2": {"pb_id": "lunar-falcon-lotus", "predictor": "boltz2", "status": "ok", "rosetta_total_per_aa": 6.202503143497149, "rosetta_fa_atr_per_aa": -5.540952144144923, "rosetta_fa_rep_per_aa": 13.233230541476269, "rosetta_fa_sol_per_aa": 3.8603505137458245, "rosetta_fa_elec_per_aa": -1.156842268178492, "rosetta_hbond_sr_bb_per_aa": 0.0, "rosetta_hbond_lr_bb_per_aa": 0.0, "rosetta_hbond_bb_sc_per_aa": -0.06912886795872063, "rosetta_hbond_sc_per_aa": -0.02610668827688089, "rosetta_rama_prepro_per_aa": 0.2149264931165009, "rosetta_fa_dun_per_aa": 2.4083923781177745, "evoef2_total_per_aa": -2.474194915254237, "budeff_total_per_aa": null, "budeff_steric_per_aa": null, "budeff_desolvation_per_aa": null, "budeff_charge_per_aa": null, "budeff_interaction_total": null, "budeff_interaction_steric": null, "budeff_interaction_desolvation": null, "budeff_interaction_charge": null, "isoelectric_point": 6.206499671936036, "molecular_weight": 25949.814299999995, "num_residues": 236, "instability_index": 39.25381355932203, "gravy": -0.288135593220339}, "chai": {"pb_id": "lunar-falcon-lotus", "predictor": "chai", "status": "ok", "rosetta_total_per_aa": 15.116640112002703, "rosetta_fa_atr_per_aa": -5.475631538315735, "rosetta_fa_rep_per_aa": 27.658958913959026, "rosetta_fa_sol_per_aa": 3.815682261600037, "rosetta_fa_elec_per_aa": -0.6548227726999126, "rosetta_hbond_sr_bb_per_aa": 0.0, "rosetta_hbond_lr_bb_per_aa": 0.0, "rosetta_hbond_bb_sc_per_aa": -0.054751233995438325, "rosetta_hbond_sc_per_aa": -0.0011324416992663454, "rosetta_rama_prepro_per_aa": 0.2851751262817027, "rosetta_fa_dun_per_aa": 2.076594719368879, "evoef2_total_per_aa": -0.7666666666666667, "budeff_total_per_aa": null, "budeff_steric_per_aa": null, "budeff_desolvation_per_aa": null, "budeff_charge_per_aa": null, "budeff_interaction_total": null, "budeff_interaction_steric": null, "budeff_interaction_desolvation": null, "budeff_interaction_charge": null, "isoelectric_point": 6.566802024841309, "molecular_weight": 16253.574799999984, "num_residues": 150, "instability_index": 29.615999999999993, "gravy": 0.28666666666666674}, "af2m": {"pb_id": "lunar-falcon-lotus", "predictor": "af2m", "status": "ok", "rosetta_total_per_aa": 240.28530350358142, "rosetta_fa_atr_per_aa": -6.3603069844558835, "rosetta_fa_rep_per_aa": 430.66705598381475, "rosetta_fa_sol_per_aa": 4.2085313827918345, "rosetta_fa_elec_per_aa": -0.887401574531922, "rosetta_hbond_sr_bb_per_aa": 0.0, "rosetta_hbond_lr_bb_per_aa": 0.0, "rosetta_hbond_bb_sc_per_aa": -0.005223105960454898, "rosetta_hbond_sc_per_aa": -0.00016100056524712654, "rosetta_rama_prepro_per_aa": 3.0494808246966656, "rosetta_fa_dun_per_aa": 5.3070544440628415, "evoef2_total_per_aa": 14.636066666666666, "budeff_total_per_aa": null, "budeff_steric_per_aa": null, "budeff_desolvation_per_aa": null, "budeff_charge_per_aa": null, "budeff_interaction_total": null, "budeff_interaction_steric": null, "budeff_interaction_desolvation": null, "budeff_interaction_charge": null, "isoelectric_point": 6.566802024841309, "molecular_weight": 16253.574799999984, "num_residues": 150, "instability_index": 29.615999999999993, "gravy": 0.28666666666666674}, "protenix": {"pb_id": "lunar-falcon-lotus", "predictor": "protenix", "status": "ok", "rosetta_total_per_aa": 9.400483692453909, "rosetta_fa_atr_per_aa": -4.710436122946391, "rosetta_fa_rep_per_aa": 16.02504826674263, "rosetta_fa_sol_per_aa": 3.3904999158230154, "rosetta_fa_elec_per_aa": -1.0413658149806588, "rosetta_hbond_sr_bb_per_aa": 0.0, "rosetta_hbond_lr_bb_per_aa": 0.0, "rosetta_hbond_bb_sc_per_aa": -0.035334669598354324, "rosetta_hbond_sc_per_aa": -0.00011601301176915625, "rosetta_rama_prepro_per_aa": 1.0008442391516572, "rosetta_fa_dun_per_aa": 2.6398031906088995, "evoef2_total_per_aa": -0.5997333333333333, "budeff_total_per_aa": null, "budeff_steric_per_aa": null, "budeff_desolvation_per_aa": null, "budeff_charge_per_aa": null, "budeff_interaction_total": null, "budeff_interaction_steric": null, "budeff_interaction_desolvation": null, "budeff_interaction_charge": null, "isoelectric_point": 6.566802024841309, "molecular_weight": 16253.574799999984, "num_residues": 150, "instability_index": 29.615999999999993, "gravy": 0.28666666666666674}}}